{
  "metadata": {
    "config": {
      "risk_loading_factor": 0.001,
      "underwriter_smoothing": 0.3,
      "distance_cost": 0.12,
      "credibility_factor": 0.2,
      "ewma_smoothing": 0.2,
      "claim_frequency": 1.0,
      "gamma_mean": 100.0,
      "gamma_std": 10.0,
      "num_insurers": 20,
      "num_customers": 1000,
      "initial_capital": 10000.0,
      "leverage_ratio": 2.0
    },
    "seed": 3033,
    "num_years": 100,
    "timestamp": "2026-02-15T19:26:34.005418+00:00",
    "git_commit": "5a7c0ea"
  },
  "market_timeseries": [
    {
      "year": 1,
      "loss_ratio": 1.0008108444807715,
      "avg_claim": 100.0,
      "total_premiums": 0.0,
      "total_claims": 0.0,
      "avg_price": 0.0,
      "min_price": 0.0,
      "max_price": 0.0,
      "num_solvent_insurers": 0,
      "herfindahl_index": 0.0,
      "gini_coefficient": 0.0
    },
    {
      "year": 2,
      "loss_ratio": 0.9968882498154438,
      "avg_claim": 100.09109255652059,
      "total_premiums": 0.0,
      "total_claims": 0.0,
      "avg_price": 0.0,
      "min_price": 0.0,
      "max_price": 0.0,
      "num_solvent_insurers": 0,
      "herfindahl_index": 0.0,
      "gini_coefficient": 0.0
    },
    {
      "year": 3,
      "loss_ratio": 0.9963780946998336,
      "avg_claim": 99.31359217286864,
      "total_premiums": 0.0,
      "total_claims": 0.0,
      "avg_price": 0.0,
      "min_price": 0.0,
      "max_price": 0.0,
      "num_solvent_insurers": 0,
      "herfindahl_index": 0.0,
      "gini_coefficient": 0.0
    },
    {
      "year": 4,
      "loss_ratio": 1.0012790810273515,
      "avg_claim": 99.7347244067916,
      "total_premiums": 0.0,
      "total_claims": 0.0,
      "avg_price": 0.0,
      "min_price": 0.0,
      "max_price": 0.0,
      "num_solvent_insurers": 0,
      "herfindahl_index": 0.0,
      "gini_coefficient": 0.0
    },
    {
      "year": 5,
      "loss_ratio": 1.0029038871763778,
      "avg_claim": 99.43736171561885,
      "total_premiums": 0.0,
      "total_claims": 0.0,
      "avg_price": 0.0,
      "min_price": 0.0,
      "max_price": 0.0,
      "num_solvent_insurers": 0,
      "herfindahl_index": 0.0,
      "gini_coefficient": 0.0
    },
    {
      "year": 6,
      "loss_ratio": 1.0008036464287828,
      "avg_claim": 99.7948703128426,
      "total_premiums": 0.0,
      "total_claims": 0.0,
      "avg_price": 0.0,
      "min_price": 0.0,
      "max_price": 0.0,
      "num_solvent_insurers": 0,
      "herfindahl_index": 0.0,
      "gini_coefficient": 0.0
    },
    {
      "year": 7,
      "loss_ratio": 0.9973585894523658,
      "avg_claim": 99.83786274353983,
      "total_premiums": 0.0,
      "total_claims": 0.0,
      "avg_price": 0.0,
      "min_price": 0.0,
      "max_price": 0.0,
      "num_solvent_insurers": 0,
      "herfindahl_index": 0.0,
      "gini_coefficient": 0.0
    },
    {
      "year": 8,
      "loss_ratio": 0.9893547394284724,
      "avg_claim": 99.67157391086931,
      "total_premiums": 0.0,
      "total_claims": 0.0,
      "avg_price": 0.0,
      "min_price": 0.0,
      "max_price": 0.0,
      "num_solvent_insurers": 0,
      "herfindahl_index": 0.0,
      "gini_coefficient": 0.0
    },
    {
      "year": 9,
      "loss_ratio": 1.0029524613894014,
      "avg_claim": 99.34792181252304,
      "total_premiums": 0.0,
      "total_claims": 0.0,
      "avg_price": 0.0,
      "min_price": 0.0,
      "max_price": 0.0,
      "num_solvent_insurers": 0,
      "herfindahl_index": 0.0,
      "gini_coefficient": 0.0
    },
    {
      "year": 10,
      "loss_ratio": 0.9994458065952518,
      "avg_claim": 100.14605363374355,
      "total_premiums": 0.0,
      "total_claims": 0.0,
      "avg_price": 0.0,
      "min_price": 0.0,
      "max_price": 0.0,
      "num_solvent_insurers": 0,
      "herfindahl_index": 0.0,
      "gini_coefficient": 0.0
    },
    {
      "year": 11,
      "loss_ratio": 0.9921578341980368,
      "avg_claim": 99.63220650134518,
      "total_premiums": 0.0,
      "total_claims": 0.0,
      "avg_price": 0.0,
      "min_price": 0.0,
      "max_price": 0.0,
      "num_solvent_insurers": 0,
      "herfindahl_index": 0.0,
      "gini_coefficient": 0.0
    },
    {
      "year": 12,
      "loss_ratio": 0.9993754804970261,
      "avg_claim": 99.81594959201286,
      "total_premiums": 0.0,
      "total_claims": 0.0,
      "avg_price": 0.0,
      "min_price": 0.0,
      "max_price": 0.0,
      "num_solvent_insurers": 0,
      "herfindahl_index": 0.0,
      "gini_coefficient": 0.0
    },
    {
      "year": 13,
      "loss_ratio": 0.9922165739505354,
      "avg_claim": 99.57272998035685,
      "total_premiums": 0.0,
      "total_claims": 0.0,
      "avg_price": 0.0,
      "min_price": 0.0,
      "max_price": 0.0,
      "num_solvent_insurers": 0,
      "herfindahl_index": 0.0,
      "gini_coefficient": 0.0
    },
    {
      "year": 14,
      "loss_ratio": 0.99075171790897,
      "avg_claim": 99.91168904123374,
      "total_premiums": 0.0,
      "total_claims": 0.0,
      "avg_price": 0.0,
      "min_price": 0.0,
      "max_price": 0.0,
      "num_solvent_insurers": 0,
      "herfindahl_index": 0.0,
      "gini_coefficient": 0.0
    },
    {
      "year": 15,
      "loss_ratio": 0.9840484281102424,
      "avg_claim": 99.75307012794883,
      "total_premiums": 0.0,
      "total_claims": 0.0,
      "avg_price": 0.0,
      "min_price": 0.0,
      "max_price": 0.0,
      "num_solvent_insurers": 0,
      "herfindahl_index": 0.0,
      "gini_coefficient": 0.0
    },
    {
      "year": 16,
      "loss_ratio": 0.9897367183191847,
      "avg_claim": 99.36495118156719,
      "total_premiums": 0.0,
      "total_claims": 0.0,
      "avg_price": 0.0,
      "min_price": 0.0,
      "max_price": 0.0,
      "num_solvent_insurers": 0,
      "herfindahl_index": 0.0,
      "gini_coefficient": 0.0
    },
    {
      "year": 17,
      "loss_ratio": 0.9971948469299842,
      "avg_claim": 99.43959357908307,
      "total_premiums": 0.0,
      "total_claims": 0.0,
      "avg_price": 0.0,
      "min_price": 0.0,
      "max_price": 0.0,
      "num_solvent_insurers": 0,
      "herfindahl_index": 0.0,
      "gini_coefficient": 0.0
    },
    {
      "year": 18,
      "loss_ratio": 0.9964120860066719,
      "avg_claim": 99.97423187954216,
      "total_premiums": 0.0,
      "total_claims": 0.0,
      "avg_price": 0.0,
      "min_price": 0.0,
      "max_price": 0.0,
      "num_solvent_insurers": 0,
      "herfindahl_index": 0.0,
      "gini_coefficient": 0.0
    },
    {
      "year": 19,
      "loss_ratio": 0.9898223873384691,
      "avg_claim": 99.90006067728837,
      "total_premiums": 0.0,
      "total_claims": 0.0,
      "avg_price": 0.0,
      "min_price": 0.0,
      "max_price": 0.0,
      "num_solvent_insurers": 0,
      "herfindahl_index": 0.0,
      "gini_coefficient": 0.0
    },
    {
      "year": 20,
      "loss_ratio": 0.9907892037515266,
      "avg_claim": 99.55054826852839,
      "total_premiums": 0.0,
      "total_claims": 0.0,
      "avg_price": 0.0,
      "min_price": 0.0,
      "max_price": 0.0,
      "num_solvent_insurers": 0,
      "herfindahl_index": 0.0,
      "gini_coefficient": 0.0
    },
    {
      "year": 21,
      "loss_ratio": 0.9992219153236828,
      "avg_claim": 99.34657533048973,
      "total_premiums": 0.0,
      "total_claims": 0.0,
      "avg_price": 0.0,
      "min_price": 0.0,
      "max_price": 0.0,
      "num_solvent_insurers": 0,
      "herfindahl_index": 0.0,
      "gini_coefficient": 0.0
    },
    {
      "year": 22,
      "loss_ratio": 0.9924341708912169,
      "avg_claim": 99.92180550118773,
      "total_premiums": 0.0,
      "total_claims": 0.0,
      "avg_price": 0.0,
      "min_price": 0.0,
      "max_price": 0.0,
      "num_solvent_insurers": 0,
      "herfindahl_index": 0.0,
      "gini_coefficient": 0.0
    },
    {
      "year": 23,
      "loss_ratio": 0.9978937643963954,
      "avg_claim": 99.28910864265238,
      "total_premiums": 0.0,
      "total_claims": 0.0,
      "avg_price": 0.0,
      "min_price": 0.0,
      "max_price": 0.0,
      "num_solvent_insurers": 0,
      "herfindahl_index": 0.0,
      "gini_coefficient": 0.0
    },
    {
      "year": 24,
      "loss_ratio": 0.9996298535345968,
      "avg_claim": 100.0307935510027,
      "total_premiums": 0.0,
      "total_claims": 0.0,
      "avg_price": 0.0,
      "min_price": 0.0,
      "max_price": 0.0,
      "num_solvent_insurers": 0,
      "herfindahl_index": 0.0,
      "gini_coefficient": 0.0
    },
    {
      "year": 25,
      "loss_ratio": 0.9967929812057755,
      "avg_claim": 99.9942260856484,
      "total_premiums": 0.0,
      "total_claims": 0.0,
      "avg_price": 0.0,
      "min_price": 0.0,
      "max_price": 0.0,
      "num_solvent_insurers": 0,
      "herfindahl_index": 0.0,
      "gini_coefficient": 0.0
    },
    {
      "year": 26,
      "loss_ratio": 0.9920332256038797,
      "avg_claim": 100.03121812428114,
      "total_premiums": 0.0,
      "total_claims": 0.0,
      "avg_price": 0.0,
      "min_price": 0.0,
      "max_price": 0.0,
      "num_solvent_insurers": 0,
      "herfindahl_index": 0.0,
      "gini_coefficient": 0.0
    },
    {
      "year": 27,
      "loss_ratio": 0.9966459932066863,
      "avg_claim": 99.9180063304494,
      "total_premiums": 0.0,
      "total_claims": 0.0,
      "avg_price": 0.0,
      "min_price": 0.0,
      "max_price": 0.0,
      "num_solvent_insurers": 0,
      "herfindahl_index": 0.0,
      "gini_coefficient": 0.0
    },
    {
      "year": 28,
      "loss_ratio": 0.9912796109771282,
      "avg_claim": 99.96812154785883,
      "total_premiums": 0.0,
      "total_claims": 0.0,
      "avg_price": 0.0,
      "min_price": 0.0,
      "max_price": 0.0,
      "num_solvent_insurers": 0,
      "herfindahl_index": 0.0,
      "gini_coefficient": 0.0
    },
    {
      "year": 29,
      "loss_ratio": 0.996002872054009,
      "avg_claim": 99.98847154607583,
      "total_premiums": 0.0,
      "total_claims": 0.0,
      "avg_price": 0.0,
      "min_price": 0.0,
      "max_price": 0.0,
      "num_solvent_insurers": 0,
      "herfindahl_index": 0.0,
      "gini_coefficient": 0.0
    },
    {
      "year": 30,
      "loss_ratio": 0.9858086120528429,
      "avg_claim": 99.95322953195753,
      "total_premiums": 0.0,
      "total_claims": 0.0,
      "avg_price": 0.0,
      "min_price": 0.0,
      "max_price": 0.0,
      "num_solvent_insurers": 0,
      "herfindahl_index": 0.0,
      "gini_coefficient": 0.0
    },
    {
      "year": 31,
      "loss_ratio": 0.9952372374799475,
      "avg_claim": 99.22901524424246,
      "total_premiums": 0.0,
      "total_claims": 0.0,
      "avg_price": 0.0,
      "min_price": 0.0,
      "max_price": 0.0,
      "num_solvent_insurers": 0,
      "herfindahl_index": 0.0,
      "gini_coefficient": 0.0
    },
    {
      "year": 32,
      "loss_ratio": 0.9966303402115924,
      "avg_claim": 99.85111574679584,
      "total_premiums": 0.0,
      "total_claims": 0.0,
      "avg_price": 0.0,
      "min_price": 0.0,
      "max_price": 0.0,
      "num_solvent_insurers": 0,
      "herfindahl_index": 0.0,
      "gini_coefficient": 0.0
    },
    {
      "year": 33,
      "loss_ratio": 0.999654334997856,
      "avg_claim": 99.73893267518501,
      "total_premiums": 0.0,
      "total_claims": 0.0,
      "avg_price": 0.0,
      "min_price": 0.0,
      "max_price": 0.0,
      "num_solvent_insurers": 0,
      "herfindahl_index": 0.0,
      "gini_coefficient": 0.0
    },
    {
      "year": 34,
      "loss_ratio": 0.9879183522585676,
      "avg_claim": 99.90112181338596,
      "total_premiums": 0.0,
      "total_claims": 0.0,
      "avg_price": 0.0,
      "min_price": 0.0,
      "max_price": 0.0,
      "num_solvent_insurers": 0,
      "herfindahl_index": 0.0,
      "gini_coefficient": 0.0
    },
    {
      "year": 35,
      "loss_ratio": 0.9885278463440071,
      "avg_claim": 99.07208266739757,
      "total_premiums": 0.0,
      "total_claims": 0.0,
      "avg_price": 0.0,
      "min_price": 0.0,
      "max_price": 0.0,
      "num_solvent_insurers": 0,
      "herfindahl_index": 0.0,
      "gini_coefficient": 0.0
    },
    {
      "year": 36,
      "loss_ratio": 1.002345389305691,
      "avg_claim": 99.37637475844534,
      "total_premiums": 0.0,
      "total_claims": 0.0,
      "avg_price": 0.0,
      "min_price": 0.0,
      "max_price": 0.0,
      "num_solvent_insurers": 0,
      "herfindahl_index": 0.0,
      "gini_coefficient": 0.0
    },
    {
      "year": 37,
      "loss_ratio": 0.9956264606009173,
      "avg_claim": 100.05305664966619,
      "total_premiums": 0.0,
      "total_claims": 0.0,
      "avg_price": 0.0,
      "min_price": 0.0,
      "max_price": 0.0,
      "num_solvent_insurers": 0,
      "herfindahl_index": 0.0,
      "gini_coefficient": 0.0
    },
    {
      "year": 38,
      "loss_ratio": 0.9968027984550224,
      "avg_claim": 99.5801544676553,
      "total_premiums": 0.0,
      "total_claims": 0.0,
      "avg_price": 0.0,
      "min_price": 0.0,
      "max_price": 0.0,
      "num_solvent_insurers": 0,
      "herfindahl_index": 0.0,
      "gini_coefficient": 0.0
    },
    {
      "year": 39,
      "loss_ratio": 0.9978310211758439,
      "avg_claim": 99.50819545878403,
      "total_premiums": 0.0,
      "total_claims": 0.0,
      "avg_price": 0.0,
      "min_price": 0.0,
      "max_price": 0.0,
      "num_solvent_insurers": 0,
      "herfindahl_index": 0.0,
      "gini_coefficient": 0.0
    },
    {
      "year": 40,
      "loss_ratio": 0.9963012994562103,
      "avg_claim": 99.92245594459195,
      "total_premiums": 0.0,
      "total_claims": 0.0,
      "avg_price": 0.0,
      "min_price": 0.0,
      "max_price": 0.0,
      "num_solvent_insurers": 0,
      "herfindahl_index": 0.0,
      "gini_coefficient": 0.0
    },
    {
      "year": 41,
      "loss_ratio": 0.9964911776566356,
      "avg_claim": 99.65411911501268,
      "total_premiums": 0.0,
      "total_claims": 0.0,
      "avg_price": 0.0,
      "min_price": 0.0,
      "max_price": 0.0,
      "num_solvent_insurers": 0,
      "herfindahl_index": 0.0,
      "gini_coefficient": 0.0
    },
    {
      "year": 42,
      "loss_ratio": 0.9977316721039718,
      "avg_claim": 99.9421184024109,
      "total_premiums": 0.0,
      "total_claims": 0.0,
      "avg_price": 0.0,
      "min_price": 0.0,
      "max_price": 0.0,
      "num_solvent_insurers": 0,
      "herfindahl_index": 0.0,
      "gini_coefficient": 0.0
    },
    {
      "year": 43,
      "loss_ratio": 0.9914925791591874,
      "avg_claim": 100.0848375417076,
      "total_premiums": 0.0,
      "total_claims": 0.0,
      "avg_price": 0.0,
      "min_price": 0.0,
      "max_price": 0.0,
      "num_solvent_insurers": 0,
      "herfindahl_index": 0.0,
      "gini_coefficient": 0.0
    },
    {
      "year": 44,
      "loss_ratio": 1.0004203087794776,
      "avg_claim": 99.5551121889904,
      "total_premiums": 0.0,
      "total_claims": 0.0,
      "avg_price": 0.0,
      "min_price": 0.0,
      "max_price": 0.0,
      "num_solvent_insurers": 0,
      "herfindahl_index": 0.0,
      "gini_coefficient": 0.0
    },
    {
      "year": 45,
      "loss_ratio": 0.9994847985073637,
      "avg_claim": 100.29426412115366,
      "total_premiums": 0.0,
      "total_claims": 0.0,
      "avg_price": 0.0,
      "min_price": 0.0,
      "max_price": 0.0,
      "num_solvent_insurers": 0,
      "herfindahl_index": 0.0,
      "gini_coefficient": 0.0
    },
    {
      "year": 46,
      "loss_ratio": 0.9908895965393449,
      "avg_claim": 100.12763857691952,
      "total_premiums": 0.0,
      "total_claims": 0.0,
      "avg_price": 0.0,
      "min_price": 0.0,
      "max_price": 0.0,
      "num_solvent_insurers": 0,
      "herfindahl_index": 0.0,
      "gini_coefficient": 0.0
    },
    {
      "year": 47,
      "loss_ratio": 0.997628335953412,
      "avg_claim": 99.78653495984108,
      "total_premiums": 0.0,
      "total_claims": 0.0,
      "avg_price": 0.0,
      "min_price": 0.0,
      "max_price": 0.0,
      "num_solvent_insurers": 0,
      "herfindahl_index": 0.0,
      "gini_coefficient": 0.0
    },
    {
      "year": 48,
      "loss_ratio": 0.9960213417146526,
      "avg_claim": 100.03534164490164,
      "total_premiums": 0.0,
      "total_claims": 0.0,
      "avg_price": 0.0,
      "min_price": 0.0,
      "max_price": 0.0,
      "num_solvent_insurers": 0,
      "herfindahl_index": 0.0,
      "gini_coefficient": 0.0
    },
    {
      "year": 49,
      "loss_ratio": 0.9901878268322347,
      "avg_claim": 99.49440536354932,
      "total_premiums": 0.0,
      "total_claims": 0.0,
      "avg_price": 0.0,
      "min_price": 0.0,
      "max_price": 0.0,
      "num_solvent_insurers": 0,
      "herfindahl_index": 0.0,
      "gini_coefficient": 0.0
    },
    {
      "year": 50,
      "loss_ratio": 1.0020739789639865,
      "avg_claim": 99.87736463622544,
      "total_premiums": 0.0,
      "total_claims": 0.0,
      "avg_price": 0.0,
      "min_price": 0.0,
      "max_price": 0.0,
      "num_solvent_insurers": 0,
      "herfindahl_index": 0.0,
      "gini_coefficient": 0.0
    },
    {
      "year": 51,
      "loss_ratio": 0.9867795891755916,
      "avg_claim": 100.12352048315547,
      "total_premiums": 0.0,
      "total_claims": 0.0,
      "avg_price": 0.0,
      "min_price": 0.0,
      "max_price": 0.0,
      "num_solvent_insurers": 0,
      "herfindahl_index": 0.0,
      "gini_coefficient": 0.0
    },
    {
      "year": 52,
      "loss_ratio": 0.9858996415722414,
      "avg_claim": 99.52266005319622,
      "total_premiums": 0.0,
      "total_claims": 0.0,
      "avg_price": 0.0,
      "min_price": 0.0,
      "max_price": 0.0,
      "num_solvent_insurers": 0,
      "herfindahl_index": 0.0,
      "gini_coefficient": 0.0
    },
    {
      "year": 53,
      "loss_ratio": 0.9962244713949232,
      "avg_claim": 99.39518350533234,
      "total_premiums": 0.0,
      "total_claims": 0.0,
      "avg_price": 0.0,
      "min_price": 0.0,
      "max_price": 0.0,
      "num_solvent_insurers": 0,
      "herfindahl_index": 0.0,
      "gini_coefficient": 0.0
    },
    {
      "year": 54,
      "loss_ratio": 0.9966529386025862,
      "avg_claim": 99.89434749400297,
      "total_premiums": 0.0,
      "total_claims": 0.0,
      "avg_price": 0.0,
      "min_price": 0.0,
      "max_price": 0.0,
      "num_solvent_insurers": 0,
      "herfindahl_index": 0.0,
      "gini_coefficient": 0.0
    },
    {
      "year": 55,
      "loss_ratio": 0.9917171808582025,
      "avg_claim": 100.33852963282295,
      "total_premiums": 0.0,
      "total_claims": 0.0,
      "avg_price": 0.0,
      "min_price": 0.0,
      "max_price": 0.0,
      "num_solvent_insurers": 0,
      "herfindahl_index": 0.0,
      "gini_coefficient": 0.0
    },
    {
      "year": 56,
      "loss_ratio": 0.9902112129630554,
      "avg_claim": 99.75360383356184,
      "total_premiums": 0.0,
      "total_claims": 0.0,
      "avg_price": 0.0,
      "min_price": 0.0,
      "max_price": 0.0,
      "num_solvent_insurers": 0,
      "herfindahl_index": 0.0,
      "gini_coefficient": 0.0
    },
    {
      "year": 57,
      "loss_ratio": 0.9917109548810169,
      "avg_claim": 99.61576828628542,
      "total_premiums": 0.0,
      "total_claims": 0.0,
      "avg_price": 0.0,
      "min_price": 0.0,
      "max_price": 0.0,
      "num_solvent_insurers": 0,
      "herfindahl_index": 0.0,
      "gini_coefficient": 0.0
    },
    {
      "year": 58,
      "loss_ratio": 0.9807191283244515,
      "avg_claim": 99.487921985416,
      "total_premiums": 0.0,
      "total_claims": 0.0,
      "avg_price": 0.0,
      "min_price": 0.0,
      "max_price": 0.0,
      "num_solvent_insurers": 0,
      "herfindahl_index": 0.0,
      "gini_coefficient": 0.0
    },
    {
      "year": 59,
      "loss_ratio": 1.002863661920676,
      "avg_claim": 98.63371363080807,
      "total_premiums": 0.0,
      "total_claims": 0.0,
      "avg_price": 0.0,
      "min_price": 0.0,
      "max_price": 0.0,
      "num_solvent_insurers": 0,
      "herfindahl_index": 0.0,
      "gini_coefficient": 0.0
    },
    {
      "year": 60,
      "loss_ratio": 1.0019949136674948,
      "avg_claim": 99.76085530686191,
      "total_premiums": 0.0,
      "total_claims": 0.0,
      "avg_price": 0.0,
      "min_price": 0.0,
      "max_price": 0.0,
      "num_solvent_insurers": 0,
      "herfindahl_index": 0.0,
      "gini_coefficient": 0.0
    },
    {
      "year": 61,
      "loss_ratio": 0.9967554933513317,
      "avg_claim": 99.60251002803808,
      "total_premiums": 0.0,
      "total_claims": 0.0,
      "avg_price": 0.0,
      "min_price": 0.0,
      "max_price": 0.0,
      "num_solvent_insurers": 0,
      "herfindahl_index": 0.0,
      "gini_coefficient": 0.0
    },
    {
      "year": 62,
      "loss_ratio": 0.9941644263086852,
      "avg_claim": 99.91513364553666,
      "total_premiums": 0.0,
      "total_claims": 0.0,
      "avg_price": 0.0,
      "min_price": 0.0,
      "max_price": 0.0,
      "num_solvent_insurers": 0,
      "herfindahl_index": 0.0,
      "gini_coefficient": 0.0
    },
    {
      "year": 63,
      "loss_ratio": 0.9961361120942325,
      "avg_claim": 99.3161373610213,
      "total_premiums": 0.0,
      "total_claims": 0.0,
      "avg_price": 0.0,
      "min_price": 0.0,
      "max_price": 0.0,
      "num_solvent_insurers": 0,
      "herfindahl_index": 0.0,
      "gini_coefficient": 0.0
    },
    {
      "year": 64,
      "loss_ratio": 1.0013936229222147,
      "avg_claim": 99.8710013225084,
      "total_premiums": 0.0,
      "total_claims": 0.0,
      "avg_price": 0.0,
      "min_price": 0.0,
      "max_price": 0.0,
      "num_solvent_insurers": 0,
      "herfindahl_index": 0.0,
      "gini_coefficient": 0.0
    },
    {
      "year": 65,
      "loss_ratio": 0.9922012005464257,
      "avg_claim": 99.93783499813628,
      "total_premiums": 0.0,
      "total_claims": 0.0,
      "avg_price": 0.0,
      "min_price": 0.0,
      "max_price": 0.0,
      "num_solvent_insurers": 0,
      "herfindahl_index": 0.0,
      "gini_coefficient": 0.0
    },
    {
      "year": 66,
      "loss_ratio": 0.9997302263420758,
      "avg_claim": 99.82083050865828,
      "total_premiums": 0.0,
      "total_claims": 0.0,
      "avg_price": 0.0,
      "min_price": 0.0,
      "max_price": 0.0,
      "num_solvent_insurers": 0,
      "herfindahl_index": 0.0,
      "gini_coefficient": 0.0
    },
    {
      "year": 67,
      "loss_ratio": 0.9907872216755583,
      "avg_claim": 100.04828603262136,
      "total_premiums": 0.0,
      "total_claims": 0.0,
      "avg_price": 0.0,
      "min_price": 0.0,
      "max_price": 0.0,
      "num_solvent_insurers": 0,
      "herfindahl_index": 0.0,
      "gini_coefficient": 0.0
    },
    {
      "year": 68,
      "loss_ratio": 0.9993387217023195,
      "avg_claim": 99.42044338981111,
      "total_premiums": 0.0,
      "total_claims": 0.0,
      "avg_price": 0.0,
      "min_price": 0.0,
      "max_price": 0.0,
      "num_solvent_insurers": 0,
      "herfindahl_index": 0.0,
      "gini_coefficient": 0.0
    },
    {
      "year": 69,
      "loss_ratio": 0.997574326986457,
      "avg_claim": 100.49558445132178,
      "total_premiums": 0.0,
      "total_claims": 0.0,
      "avg_price": 0.0,
      "min_price": 0.0,
      "max_price": 0.0,
      "num_solvent_insurers": 0,
      "herfindahl_index": 0.0,
      "gini_coefficient": 0.0
    },
    {
      "year": 70,
      "loss_ratio": 1.0002125238172657,
      "avg_claim": 100.06899916299203,
      "total_premiums": 0.0,
      "total_claims": 0.0,
      "avg_price": 0.0,
      "min_price": 0.0,
      "max_price": 0.0,
      "num_solvent_insurers": 0,
      "herfindahl_index": 0.0,
      "gini_coefficient": 0.0
    },
    {
      "year": 71,
      "loss_ratio": 0.9983691911746364,
      "avg_claim": 100.62146537457453,
      "total_premiums": 0.0,
      "total_claims": 0.0,
      "avg_price": 0.0,
      "min_price": 0.0,
      "max_price": 0.0,
      "num_solvent_insurers": 0,
      "herfindahl_index": 0.0,
      "gini_coefficient": 0.0
    },
    {
      "year": 72,
      "loss_ratio": 0.9862453967262318,
      "avg_claim": 100.4712218326494,
      "total_premiums": 0.0,
      "total_claims": 0.0,
      "avg_price": 0.0,
      "min_price": 0.0,
      "max_price": 0.0,
      "num_solvent_insurers": 0,
      "herfindahl_index": 0.0,
      "gini_coefficient": 0.0
    },
    {
      "year": 73,
      "loss_ratio": 0.9984500928179112,
      "avg_claim": 99.41055709716163,
      "total_premiums": 0.0,
      "total_claims": 0.0,
      "avg_price": 0.0,
      "min_price": 0.0,
      "max_price": 0.0,
      "num_solvent_insurers": 0,
      "herfindahl_index": 0.0,
      "gini_coefficient": 0.0
    },
    {
      "year": 74,
      "loss_ratio": 0.9991600708037142,
      "avg_claim": 100.47079566329309,
      "total_premiums": 0.0,
      "total_claims": 0.0,
      "avg_price": 0.0,
      "min_price": 0.0,
      "max_price": 0.0,
      "num_solvent_insurers": 0,
      "herfindahl_index": 0.0,
      "gini_coefficient": 0.0
    },
    {
      "year": 75,
      "loss_ratio": 0.984765228415983,
      "avg_claim": 99.8261801057582,
      "total_premiums": 0.0,
      "total_claims": 0.0,
      "avg_price": 0.0,
      "min_price": 0.0,
      "max_price": 0.0,
      "num_solvent_insurers": 0,
      "herfindahl_index": 0.0,
      "gini_coefficient": 0.0
    },
    {
      "year": 76,
      "loss_ratio": 0.9971469540881285,
      "avg_claim": 99.3508148619233,
      "total_premiums": 0.0,
      "total_claims": 0.0,
      "avg_price": 0.0,
      "min_price": 0.0,
      "max_price": 0.0,
      "num_solvent_insurers": 0,
      "herfindahl_index": 0.0,
      "gini_coefficient": 0.0
    },
    {
      "year": 77,
      "loss_ratio": 0.9993333779473876,
      "avg_claim": 100.00012637594656,
      "total_premiums": 0.0,
      "total_claims": 0.0,
      "avg_price": 0.0,
      "min_price": 0.0,
      "max_price": 0.0,
      "num_solvent_insurers": 0,
      "herfindahl_index": 0.0,
      "gini_coefficient": 0.0
    },
    {
      "year": 78,
      "loss_ratio": 0.9878374225457214,
      "avg_claim": 99.8265037610835,
      "total_premiums": 0.0,
      "total_claims": 0.0,
      "avg_price": 0.0,
      "min_price": 0.0,
      "max_price": 0.0,
      "num_solvent_insurers": 0,
      "herfindahl_index": 0.0,
      "gini_coefficient": 0.0
    },
    {
      "year": 79,
      "loss_ratio": 0.9912551420244798,
      "avg_claim": 99.42885070980577,
      "total_premiums": 0.0,
      "total_claims": 0.0,
      "avg_price": 0.0,
      "min_price": 0.0,
      "max_price": 0.0,
      "num_solvent_insurers": 0,
      "herfindahl_index": 0.0,
      "gini_coefficient": 0.0
    },
    {
      "year": 80,
      "loss_ratio": 1.0002899914254397,
      "avg_claim": 99.7622651926965,
      "total_premiums": 0.0,
      "total_claims": 0.0,
      "avg_price": 0.0,
      "min_price": 0.0,
      "max_price": 0.0,
      "num_solvent_insurers": 0,
      "herfindahl_index": 0.0,
      "gini_coefficient": 0.0
    },
    {
      "year": 81,
      "loss_ratio": 0.9852088317902555,
      "avg_claim": 100.082110468028,
      "total_premiums": 0.0,
      "total_claims": 0.0,
      "avg_price": 0.0,
      "min_price": 0.0,
      "max_price": 0.0,
      "num_solvent_insurers": 0,
      "herfindahl_index": 0.0,
      "gini_coefficient": 0.0
    },
    {
      "year": 82,
      "loss_ratio": 0.995484125394396,
      "avg_claim": 99.23614043827067,
      "total_premiums": 0.0,
      "total_claims": 0.0,
      "avg_price": 0.0,
      "min_price": 0.0,
      "max_price": 0.0,
      "num_solvent_insurers": 0,
      "herfindahl_index": 0.0,
      "gini_coefficient": 0.0
    },
    {
      "year": 83,
      "loss_ratio": 0.9948388489832992,
      "avg_claim": 99.71910094779012,
      "total_premiums": 0.0,
      "total_claims": 0.0,
      "avg_price": 0.0,
      "min_price": 0.0,
      "max_price": 0.0,
      "num_solvent_insurers": 0,
      "herfindahl_index": 0.0,
      "gini_coefficient": 0.0
    },
    {
      "year": 84,
      "loss_ratio": 0.9985310705494069,
      "avg_claim": 99.43091102091392,
      "total_premiums": 0.0,
      "total_claims": 0.0,
      "avg_price": 0.0,
      "min_price": 0.0,
      "max_price": 0.0,
      "num_solvent_insurers": 0,
      "herfindahl_index": 0.0,
      "gini_coefficient": 0.0
    },
    {
      "year": 85,
      "loss_ratio": 1.0002753277074017,
      "avg_claim": 99.9883601039086,
      "total_premiums": 0.0,
      "total_claims": 0.0,
      "avg_price": 0.0,
      "min_price": 0.0,
      "max_price": 0.0,
      "num_solvent_insurers": 0,
      "herfindahl_index": 0.0,
      "gini_coefficient": 0.0
    },
    {
      "year": 86,
      "loss_ratio": 0.9911913230719126,
      "avg_claim": 100.15980269030203,
      "total_premiums": 0.0,
      "total_claims": 0.0,
      "avg_price": 0.0,
      "min_price": 0.0,
      "max_price": 0.0,
      "num_solvent_insurers": 0,
      "herfindahl_index": 0.0,
      "gini_coefficient": 0.0
    },
    {
      "year": 87,
      "loss_ratio": 0.9900098269062412,
      "avg_claim": 99.42148152825338,
      "total_premiums": 0.0,
      "total_claims": 0.0,
      "avg_price": 0.0,
      "min_price": 0.0,
      "max_price": 0.0,
      "num_solvent_insurers": 0,
      "herfindahl_index": 0.0,
      "gini_coefficient": 0.0
    },
    {
      "year": 88,
      "loss_ratio": 0.9996377695127602,
      "avg_claim": 99.68027974901847,
      "total_premiums": 0.0,
      "total_claims": 0.0,
      "avg_price": 0.0,
      "min_price": 0.0,
      "max_price": 0.0,
      "num_solvent_insurers": 0,
      "herfindahl_index": 0.0,
      "gini_coefficient": 0.0
    },
    {
      "year": 89,
      "loss_ratio": 0.991446735146692,
      "avg_claim": 99.7476818299724,
      "total_premiums": 0.0,
      "total_claims": 0.0,
      "avg_price": 0.0,
      "min_price": 0.0,
      "max_price": 0.0,
      "num_solvent_insurers": 0,
      "herfindahl_index": 0.0,
      "gini_coefficient": 0.0
    },
    {
      "year": 90,
      "loss_ratio": 0.9904066932329332,
      "avg_claim": 99.5375802183499,
      "total_premiums": 0.0,
      "total_claims": 0.0,
      "avg_price": 0.0,
      "min_price": 0.0,
      "max_price": 0.0,
      "num_solvent_insurers": 0,
      "herfindahl_index": 0.0,
      "gini_coefficient": 0.0
    },
    {
      "year": 91,
      "loss_ratio": 0.9947393634503179,
      "avg_claim": 99.35186094651316,
      "total_premiums": 0.0,
      "total_claims": 0.0,
      "avg_price": 0.0,
      "min_price": 0.0,
      "max_price": 0.0,
      "num_solvent_insurers": 0,
      "herfindahl_index": 0.0,
      "gini_coefficient": 0.0
    },
    {
      "year": 92,
      "loss_ratio": 1.0057841276841843,
      "avg_claim": 99.30855405795074,
      "total_premiums": 0.0,
      "total_claims": 0.0,
      "avg_price": 0.0,
      "min_price": 0.0,
      "max_price": 0.0,
      "num_solvent_insurers": 0,
      "herfindahl_index": 0.0,
      "gini_coefficient": 0.0
    },
    {
      "year": 93,
      "loss_ratio": 0.9990956127405766,
      "avg_claim": 100.11356147218318,
      "total_premiums": 0.0,
      "total_claims": 0.0,
      "avg_price": 0.0,
      "min_price": 0.0,
      "max_price": 0.0,
      "num_solvent_insurers": 0,
      "herfindahl_index": 0.0,
      "gini_coefficient": 0.0
    },
    {
      "year": 94,
      "loss_ratio": 0.9887198557026002,
      "avg_claim": 99.72498662403997,
      "total_premiums": 0.0,
      "total_claims": 0.0,
      "avg_price": 0.0,
      "min_price": 0.0,
      "max_price": 0.0,
      "num_solvent_insurers": 0,
      "herfindahl_index": 0.0,
      "gini_coefficient": 0.0
    },
    {
      "year": 95,
      "loss_ratio": 1.0004632346478952,
      "avg_claim": 99.52957307334282,
      "total_premiums": 0.0,
      "total_claims": 0.0,
      "avg_price": 0.0,
      "min_price": 0.0,
      "max_price": 0.0,
      "num_solvent_insurers": 0,
      "herfindahl_index": 0.0,
      "gini_coefficient": 0.0
    },
    {
      "year": 96,
      "loss_ratio": 0.9986024258400376,
      "avg_claim": 100.01126719561493,
      "total_premiums": 0.0,
      "total_claims": 0.0,
      "avg_price": 0.0,
      "min_price": 0.0,
      "max_price": 0.0,
      "num_solvent_insurers": 0,
      "herfindahl_index": 0.0,
      "gini_coefficient": 0.0
    },
    {
      "year": 97,
      "loss_ratio": 0.9962994268189752,
      "avg_claim": 99.98901386278824,
      "total_premiums": 0.0,
      "total_claims": 0.0,
      "avg_price": 0.0,
      "min_price": 0.0,
      "max_price": 0.0,
      "num_solvent_insurers": 0,
      "herfindahl_index": 0.0,
      "gini_coefficient": 0.0
    },
    {
      "year": 98,
      "loss_ratio": 0.9995562840004274,
      "avg_claim": 99.91931395386803,
      "total_premiums": 0.0,
      "total_claims": 0.0,
      "avg_price": 0.0,
      "min_price": 0.0,
      "max_price": 0.0,
      "num_solvent_insurers": 0,
      "herfindahl_index": 0.0,
      "gini_coefficient": 0.0
    },
    {
      "year": 99,
      "loss_ratio": 0.9914900434991207,
      "avg_claim": 100.19077710078847,
      "total_premiums": 100331.27615401975,
      "total_claims": 99477.46135827134,
      "avg_price": 101.10974843880804,
      "min_price": 99.30998199710767,
      "max_price": 102.47038298803817,
      "num_solvent_insurers": 20,
      "herfindahl_index": 0.0,
      "gini_coefficient": 0.0
    }
  ],
  "insurer_snapshots": [
    {
      "year": 100,
      "insurer_id": 1,
      "capital": 12133.858375474338,
      "market_share": 0.0,
      "price": 99.74424148166572,
      "markup": 0.0043856497585238715,
      "loss_ratio": 0.995747662245329,
      "num_customers": 146,
      "is_solvent": true
    },
    {
      "year": 100,
      "insurer_id": 10,
      "capital": 12076.412912458178,
      "market_share": 0.0,
      "price": 101.65714617601296,
      "markup": 0.008676580610851671,
      "loss_ratio": 0.9958725998317338,
      "num_customers": 13,
      "is_solvent": true
    },
    {
      "year": 100,
      "insurer_id": 15,
      "capital": 14183.325495821107,
      "market_share": 0.0,
      "price": 101.13258341492273,
      "markup": 0.011049704952847333,
      "loss_ratio": 0.9922912122166284,
      "num_customers": 38,
      "is_solvent": true
    },
    {
      "year": 100,
      "insurer_id": 18,
      "capital": 12740.48729929631,
      "market_share": 0.0,
      "price": 101.66208833208539,
      "markup": 0.017869303271639488,
      "loss_ratio": 0.9946166395213125,
      "num_customers": 18,
      "is_solvent": true
    },
    {
      "year": 100,
      "insurer_id": 9,
      "capital": 13387.08556635377,
      "market_share": 0.0,
      "price": 102.17982186388777,
      "markup": 0.006744909751965273,
      "loss_ratio": 0.9930741595179023,
      "num_customers": 3,
      "is_solvent": true
    },
    {
      "year": 100,
      "insurer_id": 16,
      "capital": 13085.902521947311,
      "market_share": 0.0,
      "price": 100.96743484697868,
      "markup": 0.008867302224600691,
      "loss_ratio": 0.9936453019036028,
      "num_customers": 48,
      "is_solvent": true
    },
    {
      "year": 100,
      "insurer_id": 17,
      "capital": 11694.904563004171,
      "market_share": 0.0,
      "price": 100.8685800431138,
      "markup": 0.010695688604795495,
      "loss_ratio": 0.9962988727124211,
      "num_customers": 41,
      "is_solvent": true
    },
    {
      "year": 100,
      "insurer_id": 0,
      "capital": 11778.041177432078,
      "market_share": 0.0,
      "price": 101.63207629627803,
      "markup": 0.01590179979083922,
      "loss_ratio": 0.9964965776113324,
      "num_customers": 18,
      "is_solvent": true
    },
    {
      "year": 100,
      "insurer_id": 4,
      "capital": 12070.179093573517,
      "market_share": 0.0,
      "price": 101.60590169801023,
      "markup": 0.008587787891044127,
      "loss_ratio": 0.9959456094006651,
      "num_customers": 18,
      "is_solvent": true
    },
    {
      "year": 100,
      "insurer_id": 7,
      "capital": 14163.809270595382,
      "market_share": 0.0,
      "price": 100.29337615650368,
      "markup": 0.00826614551840649,
      "loss_ratio": 0.9922360599300003,
      "num_customers": 88,
      "is_solvent": true
    },
    {
      "year": 100,
      "insurer_id": 2,
      "capital": 11443.738171407791,
      "market_share": 0.0,
      "price": 101.74909129894746,
      "markup": 0.00653862337017222,
      "loss_ratio": 0.9967765441244778,
      "num_customers": 11,
      "is_solvent": true
    },
    {
      "year": 100,
      "insurer_id": 14,
      "capital": 13645.445297466353,
      "market_share": 0.0,
      "price": 102.47038298803817,
      "markup": 0.0113009975985611,
      "loss_ratio": 0.9931957856153927,
      "num_customers": 4,
      "is_solvent": true
    },
    {
      "year": 100,
      "insurer_id": 6,
      "capital": 12310.90006385672,
      "market_share": 0.0,
      "price": 99.30998199710767,
      "markup": 0.009603142057205125,
      "loss_ratio": 0.9952831743877336,
      "num_customers": 174,
      "is_solvent": true
    },
    {
      "year": 100,
      "insurer_id": 8,
      "capital": 13306.383034428112,
      "market_share": 0.0,
      "price": 101.6214854996753,
      "markup": 0.0035932897376903276,
      "loss_ratio": 0.9938697123425757,
      "num_customers": 10,
      "is_solvent": true
    },
    {
      "year": 100,
      "insurer_id": 11,
      "capital": 11173.400805608628,
      "market_share": 0.0,
      "price": 100.25031301281412,
      "markup": 0.008723741031060182,
      "loss_ratio": 0.9977728417466347,
      "num_customers": 105,
      "is_solvent": true
    },
    {
      "year": 100,
      "insurer_id": 13,
      "capital": 12562.277826766162,
      "market_share": 0.0,
      "price": 101.42377609591418,
      "markup": 0.008271635567235158,
      "loss_ratio": 0.9937536531636393,
      "num_customers": 20,
      "is_solvent": true
    },
    {
      "year": 100,
      "insurer_id": 12,
      "capital": 11910.564613097271,
      "market_share": 0.0,
      "price": 100.118767034356,
      "markup": 0.01015772530952235,
      "loss_ratio": 0.995854086581732,
      "num_customers": 121,
      "is_solvent": true
    },
    {
      "year": 100,
      "insurer_id": 19,
      "capital": 11981.477566787531,
      "market_share": 0.0,
      "price": 100.2334620617918,
      "markup": 0.008591520989981916,
      "loss_ratio": 0.9958640631802186,
      "num_customers": 91,
      "is_solvent": true
    },
    {
      "year": 100,
      "insurer_id": 5,
      "capital": 11044.954209940292,
      "market_share": 0.0,
      "price": 101.8377464529956,
      "markup": 0.007348248396401618,
      "loss_ratio": 0.9981439394846724,
      "num_customers": 7,
      "is_solvent": true
    },
    {
      "year": 100,
      "insurer_id": 3,
      "capital": 11440.926514007304,
      "market_share": 0.0,
      "price": 101.43671202506123,
      "markup": 0.010324783369077235,
      "loss_ratio": 0.997271419155802,
      "num_customers": 26,
      "is_solvent": true
    }
  ],
  "cycle_metrics": {
    "has_cycles": true,
    "cycle_period": 3.1,
    "dominant_frequency": 0.34,
    "mean_loss_ratio": 0.9952062801717445,
    "std_loss_ratio": 0.005070054567220668,
    "cycle_amplitude": 0.02506499935973283,
    "ar2_coefficients": [
      1.2035964400043544,
      -0.04999390110439225,
      -0.159400034589671
    ],
    "meets_cycle_conditions": false
  }
}
